[
    {
        "id": 1,
        "nome": "Luna",
        "raca": "SRD",
        "idade": "2 anos",
        "especie": "cachorro",
        "porte": "grande",
        "sexo": "Fêmea",
        "vacinado": true,
        "castrado": true,
        "localizacao": "Betim - MG",
        "descricao": "Dócil e brincalhona, adora crianças.",
        "foto": "imagens/caes/cao1.jpg"
    },
    {
        "id": 2,
        "nome": "Mingau",
        "raca": "SRD",
        "idade": "1 ano",
        "especie": "gato",
        "porte": "medio",
        "sexo": "Macho",
        "vacinado": true,
        "castrado": true,
        "localizacao": "Betim - MG",
        "descricao": "Calmo e carinhoso, ótimo para apartamento.",
        "foto": "imagens/gatos/gato1.jpg"
    },
    {
        "id": 3,
        "nome": "Thor",
        "idade": "4 anos",
        "especie": "cachorro",
        "raca": "Border Collie",
        "porte": "grande",
        "sexo": "Macho",
        "vacinado": true,
        "castrado": true,
        "localizacao": "Betim - MG",
        "descricao": "Ativo e protetor, precisa de espaço para correr.",
        "foto": "imagens/caes/cao2.jpg"
    },
    {
        "id": 4,
        "nome": "Chico",
        "idade": "1 ano",
        "especie": "gato",
        "raca": "SRD",
        "porte": "medio",
        "sexo": "Macho",
        "vacinado": true,
        "castrado": true,
        "localizacao": "Betim - MG",
        "descricao": "Ativo e protetor, precisa de espaço para correr.",
        "foto": "imagens/gatos/gato2.jpg"
    },
    {
        "id": 5,
        "nome": "Mel",
        "idade": "5 anos",
        "especie": "cachorro",
        "raca": "SRD",
        "porte": "medio",
        "sexo": "Fêmea",
        "vacinado": true,
        "castrado": true,
        "localizacao": "Betim - MG",
        "descricao": "Ativo e protetor, precisa de espaço para correr.",
        "foto": "imagens/caes/cao3.jpg"
    },
    {
        "id": 6,
        "nome": "Loki",
        "idade": "6 anos",
        "especie": "gato",
        "raca": "SRD",
        "porte": "grande",
        "sexo": "Macho",
        "vacinado": true,
        "castrado": true,
        "localizacao": "Betim - MG",
        "descricao": "Ativo e protetor, precisa de espaço para correr.",
        "foto": "imagens/gatos/gato3.jpg"
    },
    {
        "id": 7,
        "nome": "Bold",
        "idade": "1 anos",
        "especie": "cachorro",
        "raca": "Jack Russel",
        "porte": "pequeno",
        "sexo": "Macho",
        "vacinado": true,
        "castrado": true,
        "localizacao": "Betim - MG",
        "descricao": "Ativo e protetor, precisa de espaço para correr.",
        "foto": "imagens/caes/cao4.jpg"
    },
    {
        "id": 8,
        "nome": "Fred",
        "idade": "5 anos",
        "especie": "gato",
        "raca": "SRD",
        "porte": "grande",
        "sexo": "Macho",
        "vacinado": true,
        "castrado": true,
        "localizacao": "Betim - MG",
        "descricao": "Ativo e protetor, precisa de espaço para correr.",
        "foto": "imagens/gatos/gato4.jpg"
    },
    {
        "id": 9,
        "nome": "Rex",
        "especie": "cachorro",
        "raca": "SRD",
        "idade": "5 anos",
        "sexo": "Macho",
        "porte": "grande",
        "vacinado": true,
        "castrado": true,
        "localizacao": "Betim - MG",
        "descricao": "Gata dócil e tranquila, ideal para apartamento.",
        "imagem": "imagens/caes/cao5.jpeg"
    },
    {
        "id": 10,
        "nome": "Mimi",
        "especie": "gato",
        "raca": "SRD",
        "idade": "1 ano",
        "sexo": "Fêmea",
        "porte": "medio",
        "vacinado": true,
        "castrado": false,
        "localizacao": "Betim - MG",
        "descricao": "Muito brincalhão e adora crianças.",
        "imagem": "imagens/gatos/gato5.jpg"
    },
    {
        "id": 11,
        "nome": "Luna",
        "especie": "cachorro",
        "raca": "Persa",
        "idade": "3 meses",
        "sexo": "Fêmea",
        "porte": "pequeno",
        "vacinado": false,
        "castrado": false,
        "localizacao": "Ribeirão Preto - SP",
        "descricao": "Filhote ativa e carinhosa. Precisa de cuidados básicos.",
        "imagem": "imagens/caes/cao6.jpg"
    },
    {
        "id": 12,
        "nome": "Nina",
        "especie": "gato",
        "raca": "SRD",
        "idade": "6 anos",
        "sexo": "Fêmea",
        "porte": "grande",
        "vacinado": true,
        "castrado": true,
        "localizacao": "Betim - MG",
        "descricao": "Muito calma, ideal para pessoas idosas.",
        "imagem": "imagens/gatos/gato6.jpg"
    }
]